web_performance_monitor/__init__.py
web_performance_monitor/alerts.py
web_performance_monitor/analyzer.py
web_performance_monitor/cache.py
web_performance_monitor/config.py
web_performance_monitor/error_handling.py
web_performance_monitor/exceptions.py
web_performance_monitor/formatters.py
web_performance_monitor/logging_config.py
web_performance_monitor/models.py
web_performance_monitor/monitor.py
web_performance_monitor/py.typed
web_performance_monitor/utils.py
web_performance_monitor/adapters/__init__.py
web_performance_monitor/adapters/asgi.py
web_performance_monitor/adapters/base.py
web_performance_monitor/adapters/django.py
web_performance_monitor/adapters/sanic.py
web_performance_monitor/adapters/tornado.py
web_performance_monitor/adapters/wsgi.py
web_performance_monitor/middleware/__init__.py
web_performance_monitor/middleware/asgi.py
web_performance_monitor/middleware/wsgi.py
web_performance_monitor/notifiers/__init__.py
web_performance_monitor/notifiers/base.py
web_performance_monitor/notifiers/factory.py
web_performance_monitor/notifiers/local_file.py
web_performance_monitor/notifiers/mattermost.py
web_performance_monitor-1.2.3.dist-info/licenses/LICENSE
web_performance_monitor-1.2.3.dist-info/METADATA
web_performance_monitor-1.2.3.dist-info/WHEEL
web_performance_monitor-1.2.3.dist-info/top_level.txt
web_performance_monitor-1.2.3.dist-info/RECORD
