Metadata-Version: 2.4
Name: web-performance-monitor
Version: 1.2.3
Summary: 基于pyinstrument的Flask应用性能监控和告警工具
Author-email: Jahan <ambition_xu@163.com>
Maintainer-email: Jahan <ambition_xu@163.com>
License: MIT
Project-URL: Homepage, https://github.com/example/web-performance-monitor
Project-URL: Documentation, https://github.com/example/web-performance-monitor#readme
Project-URL: Repository, https://github.com/example/web-performance-monitor.git
Project-URL: Bug Tracker, https://github.com/example/web-performance-monitor/issues
Project-URL: Changelog, https://github.com/example/web-performance-monitor/blob/main/CHANGELOG.md
Keywords: flask,performance,monitoring,profiling,alerts,pyinstrument
Classifier: Development Status :: 5 - Production/Stable
Classifier: Intended Audience :: Developers
Classifier: License :: OSI Approved :: MIT License
Classifier: Programming Language :: Python :: 3
Classifier: Programming Language :: Python :: 3.7
Classifier: Programming Language :: Python :: 3.8
Classifier: Programming Language :: Python :: 3.9
Classifier: Programming Language :: Python :: 3.10
Classifier: Programming Language :: Python :: 3.11
Classifier: Framework :: Flask
Classifier: Topic :: Software Development :: Libraries :: Python Modules
Classifier: Topic :: System :: Monitoring
Classifier: Topic :: Software Development :: Quality Assurance
Classifier: Topic :: Internet :: WWW/HTTP :: WSGI :: Middleware
Requires-Python: >=3.7
License-File: LICENSE
Requires-Dist: pyinstrument>=4.0.0
Requires-Dist: flask>=2.0.0
Requires-Dist: requests>=2.25.0
Requires-Dist: mattermostdriver>=7.0.0
Provides-Extra: sanic
Requires-Dist: sanic>=21.0.0; extra == "sanic"
Provides-Extra: dev
Requires-Dist: pytest>=6.0.0; extra == "dev"
Requires-Dist: pytest-mock>=3.0.0; extra == "dev"
Requires-Dist: pytest-cov>=2.0.0; extra == "dev"
Requires-Dist: flask-testing>=0.8.0; extra == "dev"
Requires-Dist: black>=22.0.0; extra == "dev"
Requires-Dist: flake8>=4.0.0; extra == "dev"
Requires-Dist: mypy>=0.950; extra == "dev"
Provides-Extra: all
Requires-Dist: mattermostdriver>=7.0.0; extra == "all"
Requires-Dist: sanic>=21.0.0; extra == "all"
Dynamic: license-file
